README.md
setup.py
biggest/__init__.py
biggest/__main__.py
biggest/biggest.py
biggest/heap.py
biggest/tree.py
biggest.egg-info/PKG-INFO
biggest.egg-info/SOURCES.txt
biggest.egg-info/dependency_links.txt
biggest.egg-info/entry_points.txt
biggest.egg-info/requires.txt
biggest.egg-info/top_level.txt